globuslite/__init__.py
globuslite/auth.py
globuslite/config.py
globuslite/transfer.py
globuslite/version.py
globuslite/commands/__init__.py
globuslite/commands/login.py
globuslite/commands/ls.py
globuslite/commands/mkdir.py
globuslite-0.2.4.dist-info/METADATA
globuslite-0.2.4.dist-info/RECORD
globuslite-0.2.4.dist-info/WHEEL
globuslite-0.2.4.dist-info/top_level.txt
