Metadata-Version: 2.1
Name: globuslite
Version: 0.2.4
Summary: A lightweight interface to the Globus SDK.
Home-page: https://github.com/TerraFusion/globuslite
Author: Landon T. Clipp
Author-email: clipp2@illinois.edu
License: UNKNOWN
Keywords: globus,sdk,api,data,transfer,lite,lightweight,light,globuslite
Platform: UNKNOWN
Requires-Dist: configobj
Requires-Dist: pyyaml
